pumpswap_sdk/__init__.py
pumpswap_sdk/config/client.py
pumpswap_sdk/config/settings.py
pumpswap_sdk/core/__init__.py
pumpswap_sdk/core/buy_service.py
pumpswap_sdk/core/pool_service.py
pumpswap_sdk/core/price_service.py
pumpswap_sdk/core/sell_service.py
pumpswap_sdk/sdk/models.py
pumpswap_sdk/sdk/pumpswap_sdk.py
pumpswap_sdk/utils/balance.py
pumpswap_sdk/utils/constants.py
pumpswap_sdk/utils/instruction.py
pumpswap_sdk/utils/pool.py
pumpswap_sdk/utils/process_tx.py
pumpswap_sdk/utils/spl_utils.py
pumpswap_sdk/utils/token_account.py
pumpswap_sdk/utils/transaction.py
pumpswap_sdk/utils/wsol.py
pumpswap_sdk-0.1.10.dist-info/LICENSE
pumpswap_sdk-0.1.10.dist-info/METADATA
pumpswap_sdk-0.1.10.dist-info/WHEEL
pumpswap_sdk-0.1.10.dist-info/RECORD
