Metadata-Version: 2.1
Name: pumpswap-sdk
Version: 0.1.10
Summary: A Python SDK for interacting with the PumpSwap decentralized exchange (DEX) on Solana blockchain. Simplifies buying, selling, token price retrieval, and pool data access.
Home-page: https://github.com/Sajad-Salehi/PumpSwap_SDK
License: MIT
Author: Sajad
Author-email: SajadSolidity@gmail.com
Requires-Python: >=3.12,<4.0
Classifier: License :: OSI Approved :: MIT License
Classifier: Programming Language :: Python :: 3
Classifier: Programming Language :: Python :: 3.12
Classifier: Programming Language :: Python :: 3.13
Requires-Dist: base58 (>=2.1.1,<3.0.0)
Requires-Dist: pydantic (>=2.11.3,<3.0.0)
Requires-Dist: pydantic-settings (>=2.9.1,<3.0.0)
Requires-Dist: python-dotenv (>=1.1.0,<2.0.0)
Requires-Dist: solana (==0.35.1)
Requires-Dist: solders (==0.21.0)
Project-URL: Repository, https://github.com/Sajad-Salehi/PumpSwap_SDK
